rewire_fastapi/__init__.py
rewire_fastapi/dependable.py
rewire_fastapi/patch.py
rewire_fastapi/py.typed
rewire_fastapi-0.2.0.dist-info/LICENSE
rewire_fastapi-0.2.0.dist-info/METADATA
rewire_fastapi-0.2.0.dist-info/WHEEL
rewire_fastapi-0.2.0.dist-info/top_level.txt
rewire_fastapi-0.2.0.dist-info/RECORD
