Metadata-Version: 2.1
Name: rewire_fastapi
Version: 0.2.0
Summary: Fastapi integration for rewire
Author-email: Ivan Vozhakov <gou177@bk.ru>
License: MIT License
Project-URL: Homepage, https://github.com/rewirepy/rewire-fastapi
Classifier: License :: OSI Approved :: MIT License
Classifier: Programming Language :: Python
Classifier: Programming Language :: Python :: 3
Requires-Python: >=3.10
License-File: LICENSE
Requires-Dist: rewire
Requires-Dist: fastapi
Provides-Extra: hypercorn
Requires-Dist: hypercorn; extra == "hypercorn"
Provides-Extra: uvicorn
Requires-Dist: uvicorn; extra == "uvicorn"
